codex_client/__init__.py
codex_client/auth.py
codex_client/chat.py
codex_client/cli.py
codex_client/client.py
codex_client/config.py
codex_client/event.py
codex_client/exceptions.py
codex_client/structured.py
codex_client/middleware/__init__.py
codex_client/middleware/filter.py
codex_client/middleware/parser.py
codex_client/tool/__init__.py
codex_client/tool/base.py
codex_client/tool/decorator.py
codex_client/tool/server.py
examples/interactive/main.py
examples/mcp/main.py
examples/mcp/prompt.py
examples/weather/main.py
examples/weather/prompt.py
examples/weather/tool.py
examples/weather/weather.py
codex_client-0.1.0.dist-info/METADATA
codex_client-0.1.0.dist-info/WHEEL
codex_client-0.1.0.dist-info/entry_points.txt
codex_client-0.1.0.dist-info/top_level.txt
codex_client-0.1.0.dist-info/RECORD
