Metadata-Version: 2.4
Name: codex-client
Version: 0.1.0
Summary: Claude Code SDK-style wrapper around the Codex CLI for programmatic automation.
Author: Codex Assistant
Author-email: Cheowan Park <cheolwan.park552@gmail.com>
Maintainer: Codex Assistant
Maintainer-email: Cheowan Park <cheolwan.park552@gmail.com>
License: MIT
Project-URL: Homepage, https://github.com/cheolwanpark/codex-client
Project-URL: Repository, https://github.com/cheolwanpark/codex-client
Project-URL: Issues, https://github.com/cheolwanpark/codex-client/issues
Keywords: codex,openai,mcp,sdk,automation,cli
Classifier: Development Status :: 3 - Alpha
Classifier: Intended Audience :: Developers
Classifier: License :: OSI Approved :: MIT License
Classifier: Programming Language :: Python :: 3
Classifier: Programming Language :: Python :: 3 :: Only
Classifier: Programming Language :: Python :: 3.11
Classifier: Programming Language :: Python :: 3.12
Classifier: Operating System :: OS Independent
Classifier: Topic :: Software Development :: Libraries
Classifier: Topic :: Utilities
Requires-Python: >=3.11
Requires-Dist: mcp>=1.14.1
Requires-Dist: pydantic>=2.0
Requires-Dist: pytest>=7.0
Requires-Dist: fastmcp>=2.12.2
Requires-Dist: httpx>=0.27.0
